README.rst
setup.py
mustard/__init__.py
mustard/cli.py
mustard/mustard.py
mustard.egg-info/PKG-INFO
mustard.egg-info/SOURCES.txt
mustard.egg-info/dependency_links.txt
mustard.egg-info/entry_points.txt
mustard.egg-info/not-zip-safe
mustard.egg-info/requires.txt
mustard.egg-info/top_level.txt