Metadata-Version: 1.1
Name: mustard
Version: 0.1.2
Summary: DIY Docker PAAS
Home-page: https://github.com/heyman/mustard
Author: Jonatan Heyman
Author-email: jonatan@heyman.info
License: MIT
Download-URL: https://pypi.python.org/pypi/mustard
Platform: UNKNOWN
Classifier: Development Status :: 3 - Alpha
Classifier: Environment :: Console
Classifier: Intended Audience :: Developers
Classifier: Topic :: System :: Networking
Classifier: License :: OSI Approved :: MIT License
Classifier: Operating System :: OS Independent
Classifier: Programming Language :: Python
Classifier: Programming Language :: Python :: 2
Classifier: Programming Language :: Python :: 2.7
Classifier: Topic :: Software Development :: Libraries :: Python Modules
